loopleSheet/__init__.py
loopleSheet/loopleSheet.py
loopleSheet-1.0.3.dist-info/LICENCE
loopleSheet-1.0.3.dist-info/METADATA
loopleSheet-1.0.3.dist-info/WHEEL
loopleSheet-1.0.3.dist-info/top_level.txt
loopleSheet-1.0.3.dist-info/RECORD
