Metadata-Version: 2.1
Name: loopleSheet
Version: 1.0.3
Summary: subroutine wrapper connected to a Google Sheet
Home-page: https://github.com/antNLocks/loopleSheet
Author: Antoine LORENTZ
Author-email: antn.lorentz@gmail.com
License: GNU GPL v3
Requires-Python: >=3.8
License-File: LICENCE
Requires-Dist: gspread
Requires-Dist: oauth2client
